tmp/job_1/dataMem.v
// Generator : SpinalHDL v1.4.0    git head : ecb5a80b713566f417ea3ea061f9969e73770a7f
// Date      : 16/07/2021, 23:31:47
// Component : dataMem



module dataMem (
  input      [7:0]    address,
  input      [15:0]   writeData,
  output reg [15:0]   readData,
  input               memRead,
  input               memWrite,
  input               clk,
  input               reset 
);
  wire       [15:0]   _zz_2_;
  wire       [6:0]    _zz_3_;
  wire       [15:0]   content_0;
  wire       [15:0]   content_1;
  wire       [15:0]   content_2;
  wire       [15:0]   content_3;
  wire       [15:0]   content_4;
  wire       [15:0]   content_5;
  wire       [15:0]   content_6;
  wire       [15:0]   content_7;
  wire       [15:0]   content_8;
  wire       [15:0]   content_9;
  wire       [15:0]   content_10;
  wire       [15:0]   content_11;
  wire       [15:0]   content_12;
  wire       [15:0]   content_13;
  wire       [15:0]   content_14;
  wire       [15:0]   content_15;
  wire       [15:0]   content_16;
  wire       [15:0]   content_17;
  wire       [15:0]   content_18;
  wire       [15:0]   content_19;
  wire       [15:0]   content_20;
  wire       [15:0]   content_21;
  wire       [15:0]   content_22;
  wire       [15:0]   content_23;
  wire       [15:0]   content_24;
  wire       [15:0]   content_25;
  wire       [15:0]   content_26;
  wire       [15:0]   content_27;
  wire       [15:0]   content_28;
  wire       [15:0]   content_29;
  wire       [15:0]   content_30;
  wire       [15:0]   content_31;
  wire       [15:0]   content_32;
  wire       [15:0]   content_33;
  wire       [15:0]   content_34;
  wire       [15:0]   content_35;
  wire       [15:0]   content_36;
  wire       [15:0]   content_37;
  wire       [15:0]   content_38;
  wire       [15:0]   content_39;
  wire       [15:0]   content_40;
  wire       [15:0]   content_41;
  wire       [15:0]   content_42;
  wire       [15:0]   content_43;
  wire       [15:0]   content_44;
  wire       [15:0]   content_45;
  wire       [15:0]   content_46;
  wire       [15:0]   content_47;
  wire       [15:0]   content_48;
  wire       [15:0]   content_49;
  wire       [15:0]   content_50;
  wire       [15:0]   content_51;
  wire       [15:0]   content_52;
  wire       [15:0]   content_53;
  wire       [15:0]   content_54;
  wire       [15:0]   content_55;
  wire       [15:0]   content_56;
  wire       [15:0]   content_57;
  wire       [15:0]   content_58;
  wire       [15:0]   content_59;
  wire       [15:0]   content_60;
  wire       [15:0]   content_61;
  wire       [15:0]   content_62;
  wire       [15:0]   content_63;
  wire       [15:0]   content_64;
  wire       [15:0]   content_65;
  wire       [15:0]   content_66;
  wire       [15:0]   content_67;
  wire       [15:0]   content_68;
  wire       [15:0]   content_69;
  wire       [15:0]   content_70;
  wire       [15:0]   content_71;
  wire       [15:0]   content_72;
  wire       [15:0]   content_73;
  wire       [15:0]   content_74;
  wire       [15:0]   content_75;
  wire       [15:0]   content_76;
  wire       [15:0]   content_77;
  wire       [15:0]   content_78;
  wire       [15:0]   content_79;
  wire       [15:0]   content_80;
  wire       [15:0]   content_81;
  wire       [15:0]   content_82;
  wire       [15:0]   content_83;
  wire       [15:0]   content_84;
  wire       [15:0]   content_85;
  wire       [15:0]   content_86;
  wire       [15:0]   content_87;
  wire       [15:0]   content_88;
  wire       [15:0]   content_89;
  wire       [15:0]   content_90;
  wire       [15:0]   content_91;
  wire       [15:0]   content_92;
  wire       [15:0]   content_93;
  wire       [15:0]   content_94;
  wire       [15:0]   content_95;
  wire       [15:0]   content_96;
  wire       [15:0]   content_97;
  wire       [15:0]   content_98;
  wire       [15:0]   content_99;
  wire       [15:0]   content_100;
  wire       [15:0]   content_101;
  wire       [15:0]   content_102;
  wire       [15:0]   content_103;
  wire       [15:0]   content_104;
  wire       [15:0]   content_105;
  wire       [15:0]   content_106;
  wire       [15:0]   content_107;
  wire       [15:0]   content_108;
  wire       [15:0]   content_109;
  wire       [15:0]   content_110;
  wire       [15:0]   content_111;
  wire       [15:0]   content_112;
  wire       [15:0]   content_113;
  wire       [15:0]   content_114;
  wire       [15:0]   content_115;
  wire       [15:0]   content_116;
  wire       [15:0]   content_117;
  wire       [15:0]   content_118;
  wire       [15:0]   content_119;
  wire       [15:0]   content_120;
  wire       [15:0]   content_121;
  wire       [15:0]   content_122;
  wire       [15:0]   content_123;
  wire       [15:0]   content_124;
  wire       [15:0]   content_125;
  wire       [15:0]   content_126;
  wire       [15:0]   content_127;
  wire       [6:0]    _zz_1_;
  reg [15:0] mem [0:127];

  assign _zz_3_ = (address >>> 1);
  initial begin
    $readmemb("dataMem.v_toplevel_mem.bin",mem);
  end
  assign _zz_2_ = mem[_zz_1_];
  always @ (posedge clk) begin
    if(memWrite) begin
      mem[_zz_3_] <= writeData;
    end
  end

  assign content_0 = 16'h0;
  assign content_1 = 16'h0001;
  assign content_2 = 16'h0002;
  assign content_3 = 16'h0003;
  assign content_4 = 16'h0004;
  assign content_5 = 16'h0005;
  assign content_6 = 16'h0006;
  assign content_7 = 16'h0007;
  assign content_8 = 16'h0008;
  assign content_9 = 16'h0009;
  assign content_10 = 16'h000a;
  assign content_11 = 16'h000b;
  assign content_12 = 16'h000c;
  assign content_13 = 16'h000d;
  assign content_14 = 16'h000e;
  assign content_15 = 16'h000f;
  assign content_16 = 16'h0010;
  assign content_17 = 16'h0011;
  assign content_18 = 16'h0012;
  assign content_19 = 16'h0013;
  assign content_20 = 16'h0014;
  assign content_21 = 16'h0015;
  assign content_22 = 16'h0016;
  assign content_23 = 16'h0017;
  assign content_24 = 16'h0018;
  assign content_25 = 16'h0019;
  assign content_26 = 16'h001a;
  assign content_27 = 16'h001b;
  assign content_28 = 16'h001c;
  assign content_29 = 16'h001d;
  assign content_30 = 16'h001e;
  assign content_31 = 16'h001f;
  assign content_32 = 16'h0020;
  assign content_33 = 16'h0021;
  assign content_34 = 16'h0022;
  assign content_35 = 16'h0023;
  assign content_36 = 16'h0024;
  assign content_37 = 16'h0025;
  assign content_38 = 16'h0026;
  assign content_39 = 16'h0027;
  assign content_40 = 16'h0028;
  assign content_41 = 16'h0029;
  assign content_42 = 16'h002a;
  assign content_43 = 16'h002b;
  assign content_44 = 16'h002c;
  assign content_45 = 16'h002d;
  assign content_46 = 16'h002e;
  assign content_47 = 16'h002f;
  assign content_48 = 16'h0030;
  assign content_49 = 16'h0031;
  assign content_50 = 16'h0032;
  assign content_51 = 16'h0033;
  assign content_52 = 16'h0034;
  assign content_53 = 16'h0035;
  assign content_54 = 16'h0036;
  assign content_55 = 16'h0037;
  assign content_56 = 16'h0038;
  assign content_57 = 16'h0039;
  assign content_58 = 16'h003a;
  assign content_59 = 16'h003b;
  assign content_60 = 16'h003c;
  assign content_61 = 16'h003d;
  assign content_62 = 16'h003e;
  assign content_63 = 16'h003f;
  assign content_64 = 16'h0040;
  assign content_65 = 16'h0041;
  assign content_66 = 16'h0042;
  assign content_67 = 16'h0043;
  assign content_68 = 16'h0044;
  assign content_69 = 16'h0045;
  assign content_70 = 16'h0046;
  assign content_71 = 16'h0047;
  assign content_72 = 16'h0048;
  assign content_73 = 16'h0049;
  assign content_74 = 16'h004a;
  assign content_75 = 16'h004b;
  assign content_76 = 16'h004c;
  assign content_77 = 16'h004d;
  assign content_78 = 16'h004e;
  assign content_79 = 16'h004f;
  assign content_80 = 16'h0050;
  assign content_81 = 16'h0051;
  assign content_82 = 16'h0052;
  assign content_83 = 16'h0053;
  assign content_84 = 16'h0054;
  assign content_85 = 16'h0055;
  assign content_86 = 16'h0056;
  assign content_87 = 16'h0057;
  assign content_88 = 16'h0058;
  assign content_89 = 16'h0059;
  assign content_90 = 16'h005a;
  assign content_91 = 16'h005b;
  assign content_92 = 16'h005c;
  assign content_93 = 16'h005d;
  assign content_94 = 16'h005e;
  assign content_95 = 16'h005f;
  assign content_96 = 16'h0060;
  assign content_97 = 16'h0061;
  assign content_98 = 16'h0062;
  assign content_99 = 16'h0063;
  assign content_100 = 16'h0064;
  assign content_101 = 16'h0065;
  assign content_102 = 16'h0066;
  assign content_103 = 16'h0067;
  assign content_104 = 16'h0068;
  assign content_105 = 16'h0069;
  assign content_106 = 16'h006a;
  assign content_107 = 16'h006b;
  assign content_108 = 16'h006c;
  assign content_109 = 16'h006d;
  assign content_110 = 16'h006e;
  assign content_111 = 16'h006f;
  assign content_112 = 16'h0070;
  assign content_113 = 16'h0071;
  assign content_114 = 16'h0072;
  assign content_115 = 16'h0073;
  assign content_116 = 16'h0074;
  assign content_117 = 16'h0075;
  assign content_118 = 16'h0076;
  assign content_119 = 16'h0077;
  assign content_120 = 16'h0078;
  assign content_121 = 16'h0079;
  assign content_122 = 16'h007a;
  assign content_123 = 16'h007b;
  assign content_124 = 16'h007c;
  assign content_125 = 16'h007d;
  assign content_126 = 16'h007e;
  assign content_127 = 16'h007f;
  assign _zz_1_ = (address >>> 1);
  always @ (*) begin
    if(memRead)begin
      readData = _zz_2_;
    end else begin
      readData = 16'h0;
    end
  end


endmodule

simWorkspace/dataMem/test.vcd
$version Generated by VerilatedVcd $end
$date Thu Jul 15 09:56:06 2021
 $end
$timescale   1ps $end

 $scope module TOP $end
  $var wire  8 # address [7:0] $end
  $var wire  1 ( clk $end
  $var wire  1 & memRead $end
  $var wire  1 ' memWrite $end
  $var wire 16 % readData [15:0] $end
  $var wire  1 ) reset $end
  $var wire 16 $ writeData [15:0] $end
  $scope module dataMem $end
   $var wire  8 # address [7:0] $end
   $var wire  1 ( clk $end
   $var wire  1 & memRead $end
   $var wire  1 ' memWrite $end
   $var wire 16 % readData [15:0] $end
   $var wire  1 ) reset $end
   $var wire 16 $ writeData [15:0] $end
  $upscope $end
 $upscope $end
$enddefinitions $end


#0
b00000000 #
b0000000000000000 $
b0000000000000000 %
0&
1'
0(
1)
#5000
1(
#10000
0(
#15000
1(
#20000
0(
#25000
1(
#30000
0(
#35000
1(
#40000
0(
#45000
1(
#50000
0(
#55000
1(
#60000
0(
#65000
1(
#70000
0(
#75000
1(
#80000
0(
#85000
1(
#90000
0(
#95000
1(
#100000
0(
#105000
1(
#110000
0(
#115000
1(
#120000
0(
#125000
1(
#130000
0(
#135000
1(
#140000
0(
#145000
1(
#150000
0(
#155000
1(
#160000
0(
0)
#165000
b00000010 #
b0000000000000001 $
1(
#170000
0(
#175000
b00000100 #
b0000000000000010 $
1(
#180000
0(
#185000
b00000110 #
b0000000000000011 $
1(
#190000
0(
#195000
b00001000 #
b0000000000000100 $
1(
#200000
0(
#205000
b00001010 #
b0000000000000101 $
1(
#210000
0(
#215000
b00001100 #
b0000000000000110 $
1(
#220000
0(
#225000
b00001110 #
b0000000000000111 $
1(
#230000
0(
#235000
b00010000 #
b0000000000001000 $
1(
#240000
0(
#245000
b00010010 #
b0000000000001001 $
1(
#250000
0(
#255000
b00010100 #
b0000000000001010 $
1(
#260000
0(
#265000
b00010110 #
b0000000000001011 $
1(
#270000
0(
#275000
b00011000 #
b0000000000001100 $
1(
#280000
0(
#285000
b00011010 #
b0000000000001101 $
1(
#290000
0(
#295000
b00011100 #
b0000000000001110 $
1(
#300000
0(
#305000
b00011110 #
b0000000000001111 $
1(
#310000
0(
#315000
b00100000 #
b0000000000010000 $
1(
#320000
0(
#325000
b00100010 #
b0000000000010001 $
1(
#330000
0(
#335000
b00100100 #
b0000000000010010 $
1(
#340000
0(
#345000
b00100110 #
b0000000000010011 $
1(
#350000
0(
#355000
b00101000 #
b0000000000010100 $
1(
#360000
0(
#365000
b00101010 #
b0000000000010101 $
1(
#370000
0(
#375000
b00101100 #
b0000000000010110 $
1(
#380000
0(
#385000
b00101110 #
b0000000000010111 $
1(
#390000
0(
#395000
b00110000 #
b0000000000011000 $
1(
#400000
0(
#405000
b00110010 #
b0000000000011001 $
1(
#410000
0(
#415000
b00110100 #
b0000000000011010 $
1(
#420000
0(
#425000
b00110110 #
b0000000000011011 $
1(
#430000
0(
#435000
b00111000 #
b0000000000011100 $
1(
#440000
0(
#445000
b00111010 #
b0000000000011101 $
1(
#450000
0(
#455000
b00111100 #
b0000000000011110 $
1(
#460000
0(
#465000
b00111110 #
b0000000000011111 $
1(
#470000
0(
#475000
b01000000 #
b0000000000100000 $
1(
#480000
0(
#485000
b01000010 #
b0000000000100001 $
1(
#490000
0(
#495000
b01000100 #
b0000000000100010 $
1(
#500000
0(
#505000
b01000110 #
b0000000000100011 $
1(
#510000
0(
#515000
b01001000 #
b0000000000100100 $
1(
#520000
0(
#525000
b01001010 #
b0000000000100101 $
1(
#530000
0(
#535000
b01001100 #
b0000000000100110 $
1(
#540000
0(
#545000
b01001110 #
b0000000000100111 $
1(
#550000
0(
#555000
b01010000 #
b0000000000101000 $
1(
#560000
0(
#565000
b01010010 #
b0000000000101001 $
1(
#570000
0(
#575000
b01010100 #
b0000000000101010 $
1(
#580000
0(
#585000
b01010110 #
b0000000000101011 $
1(
#590000
0(
#595000
b01011000 #
b0000000000101100 $
1(
#600000
0(
#605000
b01011010 #
b0000000000101101 $
1(
#610000
0(
#615000
b01011100 #
b0000000000101110 $
1(
#620000
0(
#625000
b01011110 #
b0000000000101111 $
1(
#630000
0(
#635000
b01100000 #
b0000000000110000 $
1(
#640000
0(
#645000
b01100010 #
b0000000000110001 $
1(
#650000
0(
#655000
b01100100 #
b0000000000110010 $
1(
#660000
0(
#665000
b01100110 #
b0000000000110011 $
1(
#670000
0(
#675000
b01101000 #
b0000000000110100 $
1(
#680000
0(
#685000
b01101010 #
b0000000000110101 $
1(
#690000
0(
#695000
b01101100 #
b0000000000110110 $
1(
#700000
0(
#705000
b01101110 #
b0000000000110111 $
1(
#710000
0(
#715000
b01110000 #
b0000000000111000 $
1(
#720000
0(
#725000
b01110010 #
b0000000000111001 $
1(
#730000
0(
#735000
b01110100 #
b0000000000111010 $
1(
#740000
0(
#745000
b01110110 #
b0000000000111011 $
1(
#750000
0(
#755000
b01111000 #
b0000000000111100 $
1(
#760000
0(
#765000
b01111010 #
b0000000000111101 $
1(
#770000
0(
#775000
b01111100 #
b0000000000111110 $
1(
#780000
0(
#785000
b01111110 #
b0000000000111111 $
1(
#790000
0(
#795000
b10000000 #
b0000000001000000 $
1(
#800000
0(
#805000
b10000010 #
b0000000001000001 $
1(
#810000
0(
#815000
b10000100 #
b0000000001000010 $
1(
#820000
0(
#825000
b10000110 #
b0000000001000011 $
1(
#830000
0(
#835000
b10001000 #
b0000000001000100 $
1(
#840000
0(
#845000
b10001010 #
b0000000001000101 $
1(
#850000
0(
#855000
b10001100 #
b0000000001000110 $
1(
#860000
0(
#865000
b10001110 #
b0000000001000111 $
1(
#870000
0(
#875000
b10010000 #
b0000000001001000 $
1(
#880000
0(
#885000
b10010010 #
b0000000001001001 $
1(
#890000
0(
#895000
b10010100 #
b0000000001001010 $
1(
#900000
0(
#905000
b10010110 #
b0000000001001011 $
1(
#910000
0(
#915000
b10011000 #
b0000000001001100 $
1(
#920000
0(
#925000
b10011010 #
b0000000001001101 $
1(
#930000
0(
#935000
b10011100 #
b0000000001001110 $
1(
#940000
0(
#945000
b10011110 #
b0000000001001111 $
1(
#950000
0(
#955000
b10100000 #
b0000000001010000 $
1(
#960000
0(
#965000
b10100010 #
b0000000001010001 $
1(
#970000
0(
#975000
b10100100 #
b0000000001010010 $
1(
#980000
0(
#985000
b10100110 #
b0000000001010011 $
1(
#990000
0(
#995000
b10101000 #
b0000000001010100 $
1(
#1000000
0(
#1005000
b10101010 #
b0000000001010101 $
1(
#1010000
0(
#1015000
b10101100 #
b0000000001010110 $
1(
#1020000
0(
#1025000
b10101110 #
b0000000001010111 $
1(
#1030000
0(
#1035000
b10110000 #
b0000000001011000 $
1(
#1040000
0(
#1045000
b10110010 #
b0000000001011001 $
1(
#1050000
0(
#1055000
b10110100 #
b0000000001011010 $
1(
#1060000
0(
#1065000
b10110110 #
b0000000001011011 $
1(
#1070000
0(
#1075000
b10111000 #
b0000000001011100 $
1(
#1080000
0(
#1085000
b10111010 #
b0000000001011101 $
1(
#1090000
0(
#1095000
b10111100 #
b0000000001011110 $
1(
#1100000
0(
#1105000
b10111110 #
b0000000001011111 $
1(
#1110000
0(
#1115000
b11000000 #
b0000000001100000 $
1(
#1120000
0(
#1125000
b11000010 #
b0000000001100001 $
1(
#1130000
0(
#1135000
b11000100 #
b0000000001100010 $
1(
#1140000
0(
#1145000
b11000110 #
b0000000001100011 $
1(
#1150000
0(
#1155000
b11001000 #
b0000000001100100 $
1(
#1160000
0(
#1165000
b11001010 #
b0000000001100101 $
1(
#1170000
0(
#1175000
b11001100 #
b0000000001100110 $
1(
#1180000
0(
#1185000
b11001110 #
b0000000001100111 $
1(
#1190000
0(
#1195000
b11010000 #
b0000000001101000 $
1(
#1200000
0(
#1205000
b11010010 #
b0000000001101001 $
1(
#1210000
0(
#1215000
b11010100 #
b0000000001101010 $
1(
#1220000
0(
#1225000
b11010110 #
b0000000001101011 $
1(
#1230000
0(
#1235000
b11011000 #
b0000000001101100 $
1(
#1240000
0(
#1245000
b11011010 #
b0000000001101101 $
1(
#1250000
0(
#1255000
b11011100 #
b0000000001101110 $
1(
#1260000
0(
#1265000
b11011110 #
b0000000001101111 $
1(
#1270000
0(
#1275000
b11100000 #
b0000000001110000 $
1(
#1280000
0(
#1285000
b11100010 #
b0000000001110001 $
1(
#1290000
0(
#1295000
b11100100 #
b0000000001110010 $
1(
#1300000
0(
#1305000
b11100110 #
b0000000001110011 $
1(
#1310000
0(
#1315000
b11101000 #
b0000000001110100 $
1(
#1320000
0(
#1325000
b11101010 #
b0000000001110101 $
1(
#1330000
0(
#1335000
b11101100 #
b0000000001110110 $
1(
#1340000
0(
#1345000
b11101110 #
b0000000001110111 $
1(
#1350000
0(
#1355000
b11110000 #
b0000000001111000 $
1(
#1360000
0(
#1365000
b11110010 #
b0000000001111001 $
1(
#1370000
0(
#1375000
b11110100 #
b0000000001111010 $
1(
#1380000
0(
#1385000
b11110110 #
b0000000001111011 $
1(
#1390000
0(
#1395000
b11111000 #
b0000000001111100 $
1(
#1400000
0(
#1405000
b11111010 #
b0000000001111101 $
1(
#1410000
0(
#1415000
b11111100 #
b0000000001111110 $
1(
#1420000
0(
#1425000
b11111110 #
b0000000001111111 $
1(
#1430000
0(
#1435000
0'
1(
#1440000
0(
#1445000
b00000000 #
b0001101110110110 $
1&
1(
#1450000
0(
#1455000
b00000010 #
b1110000001000000 $
b0000000000000001 %
1(
#1460000
0(
#1465000
b00000100 #
b0010010101000000 $
b0000000000000010 %
1(
#1470000
0(
#1475000
b00000110 #
b1100101100000110 $
b0000000000000011 %
1(
#1480000
0(
#1485000
b00001000 #
b1010000010011111 $
b0000000000000100 %
1(
#1490000
0(
#1495000
b00001010 #
b0011000100110001 $
b0000000000000101 %
1(
#1500000
0(
#1505000
b00001100 #
b1101011010000011 $
b0000000000000110 %
1(
#1510000
0(
#1515000
b00001110 #
b0100011001011010 $
b0000000000000111 %
1(
#1520000
0(
#1525000
b00010000 #
b0111100111001110 $
b0000000000001000 %
1(
#1530000
0(
#1535000
b00010010 #
b1011100011001111 $
b0000000000001001 %
1(
#1540000
0(
#1545000
b00010100 #
b1001000101100111 $
b0000000000001010 %
1(
#1550000
0(
#1555000
b00010110 #
b1110000110000101 $
b0000000000001011 %
1(
#1560000
0(
#1565000
b00011000 #
b1010101101001110 $
b0000000000001100 %
1(
#1570000
0(
#1575000
b00011010 #
b0111111101001100 $
b0000000000001101 %
1(
#1580000
0(
#1585000
b00011100 #
b1010110011110001 $
b0000000000001110 %
1(
#1590000
0(
#1595000
b00011110 #
b0111000101000100 $
b0000000000001111 %
1(
#1600000
0(
#1605000
b00100000 #
b1101010010111101 $
b0000000000010000 %
1(
#1610000
0(
#1615000
b00100010 #
b0010010010001111 $
b0000000000010001 %
1(
#1620000
0(
#1625000
b00100100 #
b1100000011110111 $
b0000000000010010 %
1(
#1630000
0(
#1635000
b00100110 #
b1010100101000111 $
b0000000000010011 %
1(
#1640000
0(
#1645000
b00101000 #
b1000111111001011 $
b0000000000010100 %
1(
#1650000
0(
#1655000
b00101010 #
b1010001010110010 $
b0000000000010101 %
1(
#1660000
0(
#1665000
b00101100 #
b0110110010100101 $
b0000000000010110 %
1(
#1670000
0(
#1675000
b00101110 #
b1000011010110100 $
b0000000000010111 %
1(
#1680000
0(
#1685000
b00110000 #
b0001111010111111 $
b0000000000011000 %
1(
#1690000
0(
#1695000
b00110010 #
b1110000010000101 $
b0000000000011001 %
1(
#1700000
0(
#1705000
b00110100 #
b0110110011111010 $
b0000000000011010 %
1(
#1710000
0(
#1715000
b00110110 #
b1000101010100011 $
b0000000000011011 %
1(
#1720000
0(
#1725000
b00111000 #
b0110101011110010 $
b0000000000011100 %
1(
#1730000
0(
#1735000
b00111010 #
b0001010000001000 $
b0000000000011101 %
1(
#1740000
0(
#1745000
b00111100 #
b0000001101001100 $
b0000000000011110 %
1(
#1750000
0(
#1755000
b00111110 #
b1100010010011111 $
b0000000000011111 %
1(
#1760000
0(
#1765000
b01000000 #
b0101001101010001 $
b0000000000100000 %
1(
#1770000
0(
#1775000
b01000010 #
b1111010011110100 $
b0000000000100001 %
1(
#1780000
0(
#1785000
b01000100 #
b1010101111000000 $
b0000000000100010 %
1(
#1790000
0(
#1795000
b01000110 #
b1010110100101011 $
b0000000000100011 %
1(
#1800000
0(
#1805000
b01001000 #
b0100101011011111 $
b0000000000100100 %
1(
#1810000
0(
#1815000
b01001010 #
b1011111100110011 $
b0000000000100101 %
1(
#1820000
0(
#1825000
b01001100 #
b0010001111010011 $
b0000000000100110 %
1(
#1830000
0(
#1835000
b01001110 #
b1101000000111011 $
b0000000000100111 %
1(
#1840000
0(
#1845000
b01010000 #
b0100011100110001 $
b0000000000101000 %
1(
#1850000
0(
#1855000
b01010010 #
b0000010101100100 $
b0000000000101001 %
1(
#1860000
0(
#1865000
b01010100 #
b1100000011010100 $
b0000000000101010 %
1(
#1870000
0(
#1875000
b01010110 #
b0100011110110111 $
b0000000000101011 %
1(
#1880000
0(
#1885000
b01011000 #
b1111111011110000 $
b0000000000101100 %
1(
#1890000
0(
#1895000
b01011010 #
b0101001101011000 $
b0000000000101101 %
1(
#1900000
0(
#1905000
b01011100 #
b0001011001100111 $
b0000000000101110 %
1(
#1910000
0(
#1915000
b01011110 #
b0000010111111100 $
b0000000000101111 %
1(
#1920000
0(
#1925000
b01100000 #
b0111100001011011 $
b0000000000110000 %
1(
#1930000
0(
#1935000
b01100010 #
b1010000010011000 $
b0000000000110001 %
1(
#1940000
0(
#1945000
b01100100 #
b1110110100000011 $
b0000000000110010 %
1(
#1950000
0(
#1955000
b01100110 #
b1111000001011010 $
b0000000000110011 %
1(
#1960000
0(
#1965000
b01101000 #
b1110011111000010 $
b0000000000110100 %
1(
#1970000
0(
#1975000
b01101010 #
b1001001011011100 $
b0000000000110101 %
1(
#1980000
0(
#1985000
b01101100 #
b1000100001110101 $
b0000000000110110 %
1(
#1990000
0(
#1995000
b01101110 #
b1100100110010111 $
b0000000000110111 %
1(
#2000000
0(
#2005000
b01110000 #
b1101111000001100 $
b0000000000111000 %
1(
#2010000
0(
#2015000
b01110010 #
b1001000010010101 $
b0000000000111001 %
1(
#2020000
0(
#2025000
b01110100 #
b0011111001011011 $
b0000000000111010 %
1(
#2030000
0(
#2035000
b01110110 #
b1110110001101010 $
b0000000000111011 %
1(
#2040000
0(
#2045000
b01111000 #
b1100011100110010 $
b0000000000111100 %
1(
#2050000
0(
#2055000
b01111010 #
b1010001101100100 $
b0000000000111101 %
1(
#2060000
0(
#2065000
b01111100 #
b0101110010101010 $
b0000000000111110 %
1(
#2070000
0(
#2075000
b01111110 #
b1101011000000001 $
b0000000000111111 %
1(
#2080000
0(
#2085000
b10000000 #
b1011100011000001 $
b0000000001000000 %
1(
#2090000
0(
#2095000
b10000010 #
b0010101010100001 $
b0000000001000001 %
1(
#2100000
0(
#2105000
b10000100 #
b0110000000101001 $
b0000000001000010 %
1(
#2110000
0(
#2115000
b10000110 #
b1000000001111100 $
b0000000001000011 %
1(
#2120000
0(
#2125000
b10001000 #
b1001000001011100 $
b0000000001000100 %
1(
#2130000
0(
#2135000
b10001010 #
b0101110111010101 $
b0000000001000101 %
1(
#2140000
0(
#2145000
b10001100 #
b0111101011110011 $
b0000000001000110 %
1(
#2150000
0(
#2155000
b10001110 #
b1000110101101111 $
b0000000001000111 %
1(
#2160000
0(
#2165000
b10010000 #
b0110001000111000 $
b0000000001001000 %
1(
#2170000
0(
#2175000
b10010010 #
b1001111101000000 $
b0000000001001001 %
1(
#2180000
0(
#2185000
b10010100 #
b0110101011111001 $
b0000000001001010 %
1(
#2190000
0(
#2195000
b10010110 #
b0100000001100100 $
b0000000001001011 %
1(
#2200000
0(
#2205000
b10011000 #
b0011011110011111 $
b0000000001001100 %
1(
#2210000
0(
#2215000
b10011010 #
b1001111001010100 $
b0000000001001101 %
1(
#2220000
0(
#2225000
b10011100 #
b1010000001111110 $
b0000000001001110 %
1(
#2230000
0(
#2235000
b10011110 #
b0100100101010111 $
b0000000001001111 %
1(
#2240000
0(
#2245000
b10100000 #
b0001110101101101 $
b0000000001010000 %
1(
#2250000
0(
#2255000
b10100010 #
b0100101000110111 $
b0000000001010001 %
1(
#2260000
0(
#2265000
b10100100 #
b1011010010011001 $
b0000000001010010 %
1(
#2270000
0(
#2275000
b10100110 #
b0101111100111000 $
b0000000001010011 %
1(
#2280000
0(
#2285000
b10101000 #
b1000001010010110 $
b0000000001010100 %
1(
#2290000
0(
#2295000
b10101010 #
b1001010001000101 $
b0000000001010101 %
1(
#2300000
0(
#2305000
b10101100 #
b0010111110110110 $
b0000000001010110 %
1(
#2310000
0(
#2315000
b10101110 #
b1010101001101100 $
b0000000001010111 %
1(
#2320000
0(
#2325000
b10110000 #
b1110011010011110 $
b0000000001011000 %
1(
#2330000
0(
#2335000
b10110010 #
b0000001010001100 $
b0000000001011001 %
1(
#2340000
0(
#2345000
b10110100 #
b1010000000010101 $
b0000000001011010 %
1(
#2350000
0(
#2355000
b10110110 #
b1111111101001101 $
b0000000001011011 %
1(
#2360000
0(
#2365000
b10111000 #
b1101100000011111 $
b0000000001011100 %
1(
#2370000
0(
#2375000
b10111010 #
b0001001001001111 $
b0000000001011101 %
1(
#2380000
0(
#2385000
b10111100 #
b0000000001001010 $
b0000000001011110 %
1(
#2390000
0(
#2395000
b10111110 #
b1110100010100101 $
b0000000001011111 %
1(
#2400000
0(
#2405000
b11000000 #
b0100001101000111 $
b0000000001100000 %
1(
#2410000
0(
#2415000
b11000010 #
b0110101010000100 $
b0000000001100001 %
1(
#2420000
0(
#2425000
b11000100 #
b0110110110111011 $
b0000000001100010 %
1(
#2430000
0(
#2435000
b11000110 #
b1000001000110111 $
b0000000001100011 %
1(
#2440000
0(
#2445000
b11001000 #
b0001000001010111 $
b0000000001100100 %
1(
#2450000
0(
#2455000
b11001010 #
b1101111001010110 $
b0000000001100101 %
1(
#2460000
0(
#2465000
b11001100 #
b0010111100100110 $
b0000000001100110 %
1(
#2470000
0(
#2475000
b11001110 #
b0010001100110110 $
b0000000001100111 %
1(
#2480000
0(
#2485000
b11010000 #
b0001001000100101 $
b0000000001101000 %
1(
#2490000
0(
#2495000
b11010010 #
b0011111110100011 $
b0000000001101001 %
1(
#2500000
0(
#2505000
b11010100 #
b0000101100011000 $
b0000000001101010 %
1(
#2510000
0(
#2515000
b11010110 #
b1101100011001100 $
b0000000001101011 %
1(
#2520000
0(
#2525000
b11011000 #
b0100010010011011 $
b0000000001101100 %
1(
#2530000
0(
#2535000
b11011010 #
b0000000101111110 $
b0000000001101101 %
1(
#2540000
0(
#2545000
b11011100 #
b1110111001110110 $
b0000000001101110 %
1(
#2550000
0(
#2555000
b11011110 #
b1011000010010101 $
b0000000001101111 %
1(
#2560000
0(
#2565000
b11100000 #
b0101101100110110 $
b0000000001110000 %
1(
#2570000
0(
#2575000
b11100010 #
b1010101010101110 $
b0000000001110001 %
1(
#2580000
0(
#2585000
b11100100 #
b1110001011111000 $
b0000000001110010 %
1(
#2590000
0(
#2595000
b11100110 #
b1101001100100001 $
b0000000001110011 %
1(
#2600000
0(
#2605000
b11101000 #
b1001111110000111 $
b0000000001110100 %
1(
#2610000
0(
#2615000
b11101010 #
b0001100000101110 $
b0000000001110101 %
1(
#2620000
0(
#2625000
b11101100 #
b0101010110101001 $
b0000000001110110 %
1(
#2630000
0(
#2635000
b11101110 #
b0110111001110101 $
b0000000001110111 %
1(
#2640000
0(
#2645000
b11110000 #
b0001111110110101 $
b0000000001111000 %
1(
#2650000
0(
#2655000
b11110010 #
b1000111110101011 $
b0000000001111001 %
1(
#2660000
0(
#2665000
b11110100 #
b1010110101101001 $
b0000000001111010 %
1(
#2670000
0(
#2675000
b11110110 #
b0111000010001010 $
b0000000001111011 %
1(
#2680000
0(
#2685000
b11111000 #
b0010110011111010 $
b0000000001111100 %
1(
#2690000
0(
#2695000
b11111010 #
b1010001000001001 $
b0000000001111101 %
1(
#2700000
0(
#2705000
b11111100 #
b0011000101101011 $
b0000000001111110 %
1(
#2710000
0(
#2715000
b11111110 #
b0001000111001101 $
b0000000001111111 %
1(
