tmp/job_1/dataMem.v
// Generator : SpinalHDL v1.4.0    git head : ecb5a80b713566f417ea3ea061f9969e73770a7f
// Date      : 16/07/2021, 23:31:47
// Component : dataMem



module dataMem (
  input      [7:0]    address,
  input      [15:0]   writeData,
  output reg [15:0]   readData,
  input               memRead,
  input               memWrite,
  input               clk,
  input               reset 
);
  wire       [15:0]   _zz_2_;
  wire       [6:0]    _zz_3_;
  wire       [15:0]   content_0;
  wire       [15:0]   content_1;
  wire       [15:0]   content_2;
  wire       [15:0]   content_3;
  wire       [15:0]   content_4;
  wire       [15:0]   content_5;
  wire       [15:0]   content_6;
  wire       [15:0]   content_7;
  wire       [15:0]   content_8;
  wire       [15:0]   content_9;
  wire       [15:0]   content_10;
  wire       [15:0]   content_11;
  wire       [15:0]   content_12;
  wire       [15:0]   content_13;
  wire       [15:0]   content_14;
  wire       [15:0]   content_15;
  wire       [15:0]   content_16;
  wire       [15:0]   content_17;
  wire       [15:0]   content_18;
  wire       [15:0]   content_19;
  wire       [15:0]   content_20;
  wire       [15:0]   content_21;
  wire       [15:0]   content_22;
  wire       [15:0]   content_23;
  wire       [15:0]   content_24;
  wire       [15:0]   content_25;
  wire       [15:0]   content_26;
  wire       [15:0]   content_27;
  wire       [15:0]   content_28;
  wire       [15:0]   content_29;
  wire       [15:0]   content_30;
  wire       [15:0]   content_31;
  wire       [15:0]   content_32;
  wire       [15:0]   content_33;
  wire       [15:0]   content_34;
  wire       [15:0]   content_35;
  wire       [15:0]   content_36;
  wire       [15:0]   content_37;
  wire       [15:0]   content_38;
  wire       [15:0]   content_39;
  wire       [15:0]   content_40;
  wire       [15:0]   content_41;
  wire       [15:0]   content_42;
  wire       [15:0]   content_43;
  wire       [15:0]   content_44;
  wire       [15:0]   content_45;
  wire       [15:0]   content_46;
  wire       [15:0]   content_47;
  wire       [15:0]   content_48;
  wire       [15:0]   content_49;
  wire       [15:0]   content_50;
  wire       [15:0]   content_51;
  wire       [15:0]   content_52;
  wire       [15:0]   content_53;
  wire       [15:0]   content_54;
  wire       [15:0]   content_55;
  wire       [15:0]   content_56;
  wire       [15:0]   content_57;
  wire       [15:0]   content_58;
  wire       [15:0]   content_59;
  wire       [15:0]   content_60;
  wire       [15:0]   content_61;
  wire       [15:0]   content_62;
  wire       [15:0]   content_63;
  wire       [15:0]   content_64;
  wire       [15:0]   content_65;
  wire       [15:0]   content_66;
  wire       [15:0]   content_67;
  wire       [15:0]   content_68;
  wire       [15:0]   content_69;
  wire       [15:0]   content_70;
  wire       [15:0]   content_71;
  wire       [15:0]   content_72;
  wire       [15:0]   content_73;
  wire       [15:0]   content_74;
  wire       [15:0]   content_75;
  wire       [15:0]   content_76;
  wire       [15:0]   content_77;
  wire       [15:0]   content_78;
  wire       [15:0]   content_79;
  wire       [15:0]   content_80;
  wire       [15:0]   content_81;
  wire       [15:0]   content_82;
  wire       [15:0]   content_83;
  wire       [15:0]   content_84;
  wire       [15:0]   content_85;
  wire       [15:0]   content_86;
  wire       [15:0]   content_87;
  wire       [15:0]   content_88;
  wire       [15:0]   content_89;
  wire       [15:0]   content_90;
  wire       [15:0]   content_91;
  wire       [15:0]   content_92;
  wire       [15:0]   content_93;
  wire       [15:0]   content_94;
  wire       [15:0]   content_95;
  wire       [15:0]   content_96;
  wire       [15:0]   content_97;
  wire       [15:0]   content_98;
  wire       [15:0]   content_99;
  wire       [15:0]   content_100;
  wire       [15:0]   content_101;
  wire       [15:0]   content_102;
  wire       [15:0]   content_103;
  wire       [15:0]   content_104;
  wire       [15:0]   content_105;
  wire       [15:0]   content_106;
  wire       [15:0]   content_107;
  wire       [15:0]   content_108;
  wire       [15:0]   content_109;
  wire       [15:0]   content_110;
  wire       [15:0]   content_111;
  wire       [15:0]   content_112;
  wire       [15:0]   content_113;
  wire       [15:0]   content_114;
  wire       [15:0]   content_115;
  wire       [15:0]   content_116;
  wire       [15:0]   content_117;
  wire       [15:0]   content_118;
  wire       [15:0]   content_119;
  wire       [15:0]   content_120;
  wire       [15:0]   content_121;
  wire       [15:0]   content_122;
  wire       [15:0]   content_123;
  wire       [15:0]   content_124;
  wire       [15:0]   content_125;
  wire       [15:0]   content_126;
  wire       [15:0]   content_127;
  wire       [6:0]    _zz_1_;
  reg [15:0] mem [0:127];

  assign _zz_3_ = (address >>> 1);
  initial begin
    $readmemb("dataMem.v_toplevel_mem.bin",mem);
  end
  assign _zz_2_ = mem[_zz_1_];
  always @ (posedge clk) begin
    if(memWrite) begin
      mem[_zz_3_] <= writeData;
    end
  end

  assign content_0 = 16'h0;
  assign content_1 = 16'h0001;
  assign content_2 = 16'h0002;
  assign content_3 = 16'h0003;
  assign content_4 = 16'h0004;
  assign content_5 = 16'h0005;
  assign content_6 = 16'h0006;
  assign content_7 = 16'h0007;
  assign content_8 = 16'h0008;
  assign content_9 = 16'h0009;
  assign content_10 = 16'h000a;
  assign content_11 = 16'h000b;
  assign content_12 = 16'h000c;
  assign content_13 = 16'h000d;
  assign content_14 = 16'h000e;
  assign content_15 = 16'h000f;
  assign content_16 = 16'h0010;
  assign content_17 = 16'h0011;
  assign content_18 = 16'h0012;
  assign content_19 = 16'h0013;
  assign content_20 = 16'h0014;
  assign content_21 = 16'h0015;
  assign content_22 = 16'h0016;
  assign content_23 = 16'h0017;
  assign content_24 = 16'h0018;
  assign content_25 = 16'h0019;
  assign content_26 = 16'h001a;
  assign content_27 = 16'h001b;
  assign content_28 = 16'h001c;
  assign content_29 = 16'h001d;
  assign content_30 = 16'h001e;
  assign content_31 = 16'h001f;
  assign content_32 = 16'h0020;
  assign content_33 = 16'h0021;
  assign content_34 = 16'h0022;
  assign content_35 = 16'h0023;
  assign content_36 = 16'h0024;
  assign content_37 = 16'h0025;
  assign content_38 = 16'h0026;
  assign content_39 = 16'h0027;
  assign content_40 = 16'h0028;
  assign content_41 = 16'h0029;
  assign content_42 = 16'h002a;
  assign content_43 = 16'h002b;
  assign content_44 = 16'h002c;
  assign content_45 = 16'h002d;
  assign content_46 = 16'h002e;
  assign content_47 = 16'h002f;
  assign content_48 = 16'h0030;
  assign content_49 = 16'h0031;
  assign content_50 = 16'h0032;
  assign content_51 = 16'h0033;
  assign content_52 = 16'h0034;
  assign content_53 = 16'h0035;
  assign content_54 = 16'h0036;
  assign content_55 = 16'h0037;
  assign content_56 = 16'h0038;
  assign content_57 = 16'h0039;
  assign content_58 = 16'h003a;
  assign content_59 = 16'h003b;
  assign content_60 = 16'h003c;
  assign content_61 = 16'h003d;
  assign content_62 = 16'h003e;
  assign content_63 = 16'h003f;
  assign content_64 = 16'h0040;
  assign content_65 = 16'h0041;
  assign content_66 = 16'h0042;
  assign content_67 = 16'h0043;
  assign content_68 = 16'h0044;
  assign content_69 = 16'h0045;
  assign content_70 = 16'h0046;
  assign content_71 = 16'h0047;
  assign content_72 = 16'h0048;
  assign content_73 = 16'h0049;
  assign content_74 = 16'h004a;
  assign content_75 = 16'h004b;
  assign content_76 = 16'h004c;
  assign content_77 = 16'h004d;
  assign content_78 = 16'h004e;
  assign content_79 = 16'h004f;
  assign content_80 = 16'h0050;
  assign content_81 = 16'h0051;
  assign content_82 = 16'h0052;
  assign content_83 = 16'h0053;
  assign content_84 = 16'h0054;
  assign content_85 = 16'h0055;
  assign content_86 = 16'h0056;
  assign content_87 = 16'h0057;
  assign content_88 = 16'h0058;
  assign content_89 = 16'h0059;
  assign content_90 = 16'h005a;
  assign content_91 = 16'h005b;
  assign content_92 = 16'h005c;
  assign content_93 = 16'h005d;
  assign content_94 = 16'h005e;
  assign content_95 = 16'h005f;
  assign content_96 = 16'h0060;
  assign content_97 = 16'h0061;
  assign content_98 = 16'h0062;
  assign content_99 = 16'h0063;
  assign content_100 = 16'h0064;
  assign content_101 = 16'h0065;
  assign content_102 = 16'h0066;
  assign content_103 = 16'h0067;
  assign content_104 = 16'h0068;
  assign content_105 = 16'h0069;
  assign content_106 = 16'h006a;
  assign content_107 = 16'h006b;
  assign content_108 = 16'h006c;
  assign content_109 = 16'h006d;
  assign content_110 = 16'h006e;
  assign content_111 = 16'h006f;
  assign content_112 = 16'h0070;
  assign content_113 = 16'h0071;
  assign content_114 = 16'h0072;
  assign content_115 = 16'h0073;
  assign content_116 = 16'h0074;
  assign content_117 = 16'h0075;
  assign content_118 = 16'h0076;
  assign content_119 = 16'h0077;
  assign content_120 = 16'h0078;
  assign content_121 = 16'h0079;
  assign content_122 = 16'h007a;
  assign content_123 = 16'h007b;
  assign content_124 = 16'h007c;
  assign content_125 = 16'h007d;
  assign content_126 = 16'h007e;
  assign content_127 = 16'h007f;
  assign _zz_1_ = (address >>> 1);
  always @ (*) begin
    if(memRead)begin
      readData = _zz_2_;
    end else begin
      readData = 16'h0;
    end
  end


endmodule

simWorkspace/dataMem/test.vcd
$version Generated by VerilatedVcd $end
$date Thu Jul 15 12:57:18 2021
 $end
$timescale   1ps $end

 $scope module TOP $end
  $var wire  8 # address [7:0] $end
  $var wire  1 ( clk $end
  $var wire  1 & memRead $end
  $var wire  1 ' memWrite $end
  $var wire 16 % readData [15:0] $end
  $var wire  1 ) reset $end
  $var wire 16 $ writeData [15:0] $end
  $scope module dataMem $end
   $var wire  8 # address [7:0] $end
   $var wire  1 ( clk $end
   $var wire  1 & memRead $end
   $var wire  1 ' memWrite $end
   $var wire 16 % readData [15:0] $end
   $var wire  1 ) reset $end
   $var wire 16 $ writeData [15:0] $end
  $upscope $end
 $upscope $end
$enddefinitions $end


#0
b00000000 #
b0000000000000000 $
b0000000000000000 %
0&
1'
1(
1)
#5000
0(
#10000
1(
#15000
0(
#20000
1(
#25000
0(
#30000
1(
#35000
0(
#40000
1(
#45000
0(
#50000
1(
#55000
0(
#60000
1(
#65000
0(
#70000
1(
#75000
0(
#80000
1(
#85000
0(
#90000
1(
#95000
0(
#100000
1(
#105000
0(
#110000
1(
#115000
0(
#120000
1(
#125000
0(
#130000
1(
#135000
0(
#140000
1(
#145000
0(
#150000
1(
#155000
0(
#160000
b00000010 #
b0000000000000001 $
1(
0)
#165000
0(
#170000
b00000100 #
b0000000000000010 $
1(
#175000
0(
#180000
b00000110 #
b0000000000000011 $
1(
#185000
0(
#190000
b00001000 #
b0000000000000100 $
1(
#195000
0(
#200000
b00001010 #
b0000000000000101 $
1(
#205000
0(
#210000
b00001100 #
b0000000000000110 $
1(
#215000
0(
#220000
b00001110 #
b0000000000000111 $
1(
#225000
0(
#230000
b00010000 #
b0000000000001000 $
1(
#235000
0(
#240000
b00010010 #
b0000000000001001 $
1(
#245000
0(
#250000
b00010100 #
b0000000000001010 $
1(
#255000
0(
#260000
b00010110 #
b0000000000001011 $
1(
#265000
0(
#270000
b00011000 #
b0000000000001100 $
1(
#275000
0(
#280000
b00011010 #
b0000000000001101 $
1(
#285000
0(
#290000
b00011100 #
b0000000000001110 $
1(
#295000
0(
#300000
b00011110 #
b0000000000001111 $
1(
#305000
0(
#310000
b00100000 #
b0000000000010000 $
1(
#315000
0(
#320000
b00100010 #
b0000000000010001 $
1(
#325000
0(
#330000
b00100100 #
b0000000000010010 $
1(
#335000
0(
#340000
b00100110 #
b0000000000010011 $
1(
#345000
0(
#350000
b00101000 #
b0000000000010100 $
1(
#355000
0(
#360000
b00101010 #
b0000000000010101 $
1(
#365000
0(
#370000
b00101100 #
b0000000000010110 $
1(
#375000
0(
#380000
b00101110 #
b0000000000010111 $
1(
#385000
0(
#390000
b00110000 #
b0000000000011000 $
1(
#395000
0(
#400000
b00110010 #
b0000000000011001 $
1(
#405000
0(
#410000
b00110100 #
b0000000000011010 $
1(
#415000
0(
#420000
b00110110 #
b0000000000011011 $
1(
#425000
0(
#430000
b00111000 #
b0000000000011100 $
1(
#435000
0(
#440000
b00111010 #
b0000000000011101 $
1(
#445000
0(
#450000
b00111100 #
b0000000000011110 $
1(
#455000
0(
#460000
b00111110 #
b0000000000011111 $
1(
#465000
0(
#470000
b01000000 #
b0000000000100000 $
1(
#475000
0(
#480000
b01000010 #
b0000000000100001 $
1(
#485000
0(
#490000
b01000100 #
b0000000000100010 $
1(
#495000
0(
#500000
b01000110 #
b0000000000100011 $
1(
#505000
0(
#510000
b01001000 #
b0000000000100100 $
1(
#515000
0(
#520000
b01001010 #
b0000000000100101 $
1(
#525000
0(
#530000
b01001100 #
b0000000000100110 $
1(
#535000
0(
#540000
b01001110 #
b0000000000100111 $
1(
#545000
0(
#550000
b01010000 #
b0000000000101000 $
1(
#555000
0(
#560000
b01010010 #
b0000000000101001 $
1(
#565000
0(
#570000
b01010100 #
b0000000000101010 $
1(
#575000
0(
#580000
b01010110 #
b0000000000101011 $
1(
#585000
0(
#590000
b01011000 #
b0000000000101100 $
1(
#595000
0(
#600000
b01011010 #
b0000000000101101 $
1(
#605000
0(
#610000
b01011100 #
b0000000000101110 $
1(
#615000
0(
#620000
b01011110 #
b0000000000101111 $
1(
#625000
0(
#630000
b01100000 #
b0000000000110000 $
1(
#635000
0(
#640000
b01100010 #
b0000000000110001 $
1(
#645000
0(
#650000
b01100100 #
b0000000000110010 $
1(
#655000
0(
#660000
b01100110 #
b0000000000110011 $
1(
#665000
0(
#670000
b01101000 #
b0000000000110100 $
1(
#675000
0(
#680000
b01101010 #
b0000000000110101 $
1(
#685000
0(
#690000
b01101100 #
b0000000000110110 $
1(
#695000
0(
#700000
b01101110 #
b0000000000110111 $
1(
#705000
0(
#710000
b01110000 #
b0000000000111000 $
1(
#715000
0(
#720000
b01110010 #
b0000000000111001 $
1(
#725000
0(
#730000
b01110100 #
b0000000000111010 $
1(
#735000
0(
#740000
b01110110 #
b0000000000111011 $
1(
#745000
0(
#750000
b01111000 #
b0000000000111100 $
1(
#755000
0(
#760000
b01111010 #
b0000000000111101 $
1(
#765000
0(
#770000
b01111100 #
b0000000000111110 $
1(
#775000
0(
#780000
b01111110 #
b0000000000111111 $
1(
#785000
0(
#790000
b10000000 #
b0000000001000000 $
1(
#795000
0(
#800000
b10000010 #
b0000000001000001 $
1(
#805000
0(
#810000
b10000100 #
b0000000001000010 $
1(
#815000
0(
#820000
b10000110 #
b0000000001000011 $
1(
#825000
0(
#830000
b10001000 #
b0000000001000100 $
1(
#835000
0(
#840000
b10001010 #
b0000000001000101 $
1(
#845000
0(
#850000
b10001100 #
b0000000001000110 $
1(
#855000
0(
#860000
b10001110 #
b0000000001000111 $
1(
#865000
0(
#870000
b10010000 #
b0000000001001000 $
1(
#875000
0(
#880000
b10010010 #
b0000000001001001 $
1(
#885000
0(
#890000
b10010100 #
b0000000001001010 $
1(
#895000
0(
#900000
b10010110 #
b0000000001001011 $
1(
#905000
0(
#910000
b10011000 #
b0000000001001100 $
1(
#915000
0(
#920000
b10011010 #
b0000000001001101 $
1(
#925000
0(
#930000
b10011100 #
b0000000001001110 $
1(
#935000
0(
#940000
b10011110 #
b0000000001001111 $
1(
#945000
0(
#950000
b10100000 #
b0000000001010000 $
1(
#955000
0(
#960000
b10100010 #
b0000000001010001 $
1(
#965000
0(
#970000
b10100100 #
b0000000001010010 $
1(
#975000
0(
#980000
b10100110 #
b0000000001010011 $
1(
#985000
0(
#990000
b10101000 #
b0000000001010100 $
1(
#995000
0(
#1000000
b10101010 #
b0000000001010101 $
1(
#1005000
0(
#1010000
b10101100 #
b0000000001010110 $
1(
#1015000
0(
#1020000
b10101110 #
b0000000001010111 $
1(
#1025000
0(
#1030000
b10110000 #
b0000000001011000 $
1(
#1035000
0(
#1040000
b10110010 #
b0000000001011001 $
1(
#1045000
0(
#1050000
b10110100 #
b0000000001011010 $
1(
#1055000
0(
#1060000
b10110110 #
b0000000001011011 $
1(
#1065000
0(
#1070000
b10111000 #
b0000000001011100 $
1(
#1075000
0(
#1080000
b10111010 #
b0000000001011101 $
1(
#1085000
0(
#1090000
b10111100 #
b0000000001011110 $
1(
#1095000
0(
#1100000
b10111110 #
b0000000001011111 $
1(
#1105000
0(
#1110000
b11000000 #
b0000000001100000 $
1(
#1115000
0(
#1120000
b11000010 #
b0000000001100001 $
1(
#1125000
0(
#1130000
b11000100 #
b0000000001100010 $
1(
#1135000
0(
#1140000
b11000110 #
b0000000001100011 $
1(
#1145000
0(
#1150000
b11001000 #
b0000000001100100 $
1(
#1155000
0(
#1160000
b11001010 #
b0000000001100101 $
1(
#1165000
0(
#1170000
b11001100 #
b0000000001100110 $
1(
#1175000
0(
#1180000
b11001110 #
b0000000001100111 $
1(
#1185000
0(
#1190000
b11010000 #
b0000000001101000 $
1(
#1195000
0(
#1200000
b11010010 #
b0000000001101001 $
1(
#1205000
0(
#1210000
b11010100 #
b0000000001101010 $
1(
#1215000
0(
#1220000
b11010110 #
b0000000001101011 $
1(
#1225000
0(
#1230000
b11011000 #
b0000000001101100 $
1(
#1235000
0(
#1240000
b11011010 #
b0000000001101101 $
1(
#1245000
0(
#1250000
b11011100 #
b0000000001101110 $
1(
#1255000
0(
#1260000
b11011110 #
b0000000001101111 $
1(
#1265000
0(
#1270000
b11100000 #
b0000000001110000 $
1(
#1275000
0(
#1280000
b11100010 #
b0000000001110001 $
1(
#1285000
0(
#1290000
b11100100 #
b0000000001110010 $
1(
#1295000
0(
#1300000
b11100110 #
b0000000001110011 $
1(
#1305000
0(
#1310000
b11101000 #
b0000000001110100 $
1(
#1315000
0(
#1320000
b11101010 #
b0000000001110101 $
1(
#1325000
0(
#1330000
b11101100 #
b0000000001110110 $
1(
#1335000
0(
#1340000
b11101110 #
b0000000001110111 $
1(
#1345000
0(
#1350000
b11110000 #
b0000000001111000 $
1(
#1355000
0(
#1360000
b11110010 #
b0000000001111001 $
1(
#1365000
0(
#1370000
b11110100 #
b0000000001111010 $
1(
#1375000
0(
#1380000
b11110110 #
b0000000001111011 $
1(
#1385000
0(
#1390000
b11111000 #
b0000000001111100 $
1(
#1395000
0(
#1400000
b11111010 #
b0000000001111101 $
1(
#1405000
0(
#1410000
b11111100 #
b0000000001111110 $
1(
#1415000
0(
#1420000
b11111110 #
b0000000001111111 $
1(
#1425000
0(
#1430000
0'
1(
#1435000
0(
#1440000
b00000000 #
b1001111110111001 $
1&
1(
#1445000
0(
#1450000
b00000010 #
b1101111101000001 $
b0000000000000001 %
1(
#1455000
0(
#1460000
b00000100 #
b1100010010101011 $
b0000000000000010 %
1(
#1465000
0(
#1470000
b00000110 #
b0000000110110100 $
b0000000000000011 %
1(
#1475000
0(
#1480000
b00001000 #
b1100110101011100 $
b0000000000000100 %
1(
#1485000
0(
#1490000
b00001010 #
b0001100001000001 $
b0000000000000101 %
1(
#1495000
0(
#1500000
b00001100 #
b1100010000011110 $
b0000000000000110 %
1(
#1505000
0(
#1510000
b00001110 #
b0001101010000000 $
b0000000000000111 %
1(
#1515000
0(
#1520000
b00010000 #
b1011111100101100 $
b0000000000001000 %
1(
#1525000
0(
#1530000
b00010010 #
b1111010011001111 $
b0000000000001001 %
1(
#1535000
0(
#1540000
b00010100 #
b1100111011101110 $
b0000000000001010 %
1(
#1545000
0(
#1550000
b00010110 #
b1110101000110001 $
b0000000000001011 %
1(
#1555000
0(
#1560000
b00011000 #
b0000110001111011 $
b0000000000001100 %
1(
#1565000
0(
#1570000
b00011010 #
b1011000001110011 $
b0000000000001101 %
1(
#1575000
0(
#1580000
b00011100 #
b1000110001100000 $
b0000000000001110 %
1(
#1585000
0(
#1590000
b00011110 #
b1010101010010000 $
b0000000000001111 %
1(
#1595000
0(
#1600000
b00100000 #
b0011100110011111 $
b0000000000010000 %
1(
#1605000
0(
#1610000
b00100010 #
b1110010101010110 $
b0000000000010001 %
1(
#1615000
0(
#1620000
b00100100 #
b1101110011111010 $
b0000000000010010 %
1(
#1625000
0(
#1630000
b00100110 #
b1011101001001000 $
b0000000000010011 %
1(
#1635000
0(
#1640000
b00101000 #
b1101010001110000 $
b0000000000010100 %
1(
#1645000
0(
#1650000
b00101010 #
b0011110011000110 $
b0000000000010101 %
1(
#1655000
0(
#1660000
b00101100 #
b0011111100001000 $
b0000000000010110 %
1(
#1665000
0(
#1670000
b00101110 #
b1101010101101011 $
b0000000000010111 %
1(
#1675000
0(
#1680000
b00110000 #
b1010000011001100 $
b0000000000011000 %
1(
#1685000
0(
#1690000
b00110010 #
b1010111110110110 $
b0000000000011001 %
1(
#1695000
0(
#1700000
b00110100 #
b0100001100011000 $
b0000000000011010 %
1(
#1705000
0(
#1710000
b00110110 #
b1101110111101011 $
b0000000000011011 %
1(
#1715000
0(
#1720000
b00111000 #
b1101010100010100 $
b0000000000011100 %
1(
#1725000
0(
#1730000
b00111010 #
b0101011100111011 $
b0000000000011101 %
1(
#1735000
0(
#1740000
b00111100 #
b0001000001111110 $
b0000000000011110 %
1(
#1745000
0(
#1750000
b00111110 #
b0011010000100010 $
b0000000000011111 %
1(
#1755000
0(
#1760000
b01000000 #
b0110011010101100 $
b0000000000100000 %
1(
#1765000
0(
#1770000
b01000010 #
b1100110100010000 $
b0000000000100001 %
1(
#1775000
0(
#1780000
b01000100 #
b1111100111010001 $
b0000000000100010 %
1(
#1785000
0(
#1790000
b01000110 #
b1001111101001011 $
b0000000000100011 %
1(
#1795000
0(
#1800000
b01001000 #
b0110011001111110 $
b0000000000100100 %
1(
#1805000
0(
#1810000
b01001010 #
b0001110000010011 $
b0000000000100101 %
1(
#1815000
0(
#1820000
b01001100 #
b0010000101101100 $
b0000000000100110 %
1(
#1825000
0(
#1830000
b01001110 #
b1100011000000110 $
b0000000000100111 %
1(
#1835000
0(
#1840000
b01010000 #
b0110110101111000 $
b0000000000101000 %
1(
#1845000
0(
#1850000
b01010010 #
b0100000011000101 $
b0000000000101001 %
1(
#1855000
0(
#1860000
b01010100 #
b0010110111101110 $
b0000000000101010 %
1(
#1865000
0(
#1870000
b01010110 #
b0011011011011000 $
b0000000000101011 %
1(
#1875000
0(
#1880000
b01011000 #
b0001100100001001 $
b0000000000101100 %
1(
#1885000
0(
#1890000
b01011010 #
b0011100111001110 $
b0000000000101101 %
1(
#1895000
0(
#1900000
b01011100 #
b0000111010111010 $
b0000000000101110 %
1(
#1905000
0(
#1910000
b01011110 #
b0000000010101000 $
b0000000000101111 %
1(
#1915000
0(
#1920000
b01100000 #
b1001011110101000 $
b0000000000110000 %
1(
#1925000
0(
#1930000
b01100010 #
b1010100001110111 $
b0000000000110001 %
1(
#1935000
0(
#1940000
b01100100 #
b1101000001111000 $
b0000000000110010 %
1(
#1945000
0(
#1950000
b01100110 #
b1101101101000100 $
b0000000000110011 %
1(
#1955000
0(
#1960000
b01101000 #
b0100010101001101 $
b0000000000110100 %
1(
#1965000
0(
#1970000
b01101010 #
b0000000100101111 $
b0000000000110101 %
1(
#1975000
0(
#1980000
b01101100 #
b1000000110010010 $
b0000000000110110 %
1(
#1985000
0(
#1990000
b01101110 #
b1101111111011010 $
b0000000000110111 %
1(
#1995000
0(
#2000000
b01110000 #
b0101011111110110 $
b0000000000111000 %
1(
#2005000
0(
#2010000
b01110010 #
b0100110000000111 $
b0000000000111001 %
1(
#2015000
0(
#2020000
b01110100 #
b0010011010111000 $
b0000000000111010 %
1(
#2025000
0(
#2030000
b01110110 #
b1101000101111111 $
b0000000000111011 %
1(
#2035000
0(
#2040000
b01111000 #
b1001110000100100 $
b0000000000111100 %
1(
#2045000
0(
#2050000
b01111010 #
b0111010100110101 $
b0000000000111101 %
1(
#2055000
0(
#2060000
b01111100 #
b1011111101011100 $
b0000000000111110 %
1(
#2065000
0(
#2070000
b01111110 #
b1111010110101011 $
b0000000000111111 %
1(
#2075000
0(
#2080000
b10000000 #
b0100000101011011 $
b0000000001000000 %
1(
#2085000
0(
#2090000
b10000010 #
b0010110110010101 $
b0000000001000001 %
1(
#2095000
0(
#2100000
b10000100 #
b0101101000110111 $
b0000000001000010 %
1(
#2105000
0(
#2110000
b10000110 #
b0111110010111011 $
b0000000001000011 %
1(
#2115000
0(
#2120000
b10001000 #
b1011011010100110 $
b0000000001000100 %
1(
#2125000
0(
#2130000
b10001010 #
b0101101100100011 $
b0000000001000101 %
1(
#2135000
0(
#2140000
b10001100 #
b0011100111000010 $
b0000000001000110 %
1(
#2145000
0(
#2150000
b10001110 #
b0111101001101110 $
b0000000001000111 %
1(
#2155000
0(
#2160000
b10010000 #
b1001011100010000 $
b0000000001001000 %
1(
#2165000
0(
#2170000
b10010010 #
b0001100110000010 $
b0000000001001001 %
1(
#2175000
0(
#2180000
b10010100 #
b0000100010111110 $
b0000000001001010 %
1(
#2185000
0(
#2190000
b10010110 #
b0110111001101001 $
b0000000001001011 %
1(
#2195000
0(
#2200000
b10011000 #
b1010011000101011 $
b0000000001001100 %
1(
#2205000
0(
#2210000
b10011010 #
b0100101001111000 $
b0000000001001101 %
1(
#2215000
0(
#2220000
b10011100 #
b0001111010101101 $
b0000000001001110 %
1(
#2225000
0(
#2230000
b10011110 #
b0101110010110011 $
b0000000001001111 %
1(
#2235000
0(
#2240000
b10100000 #
b1101110010001101 $
b0000000001010000 %
1(
#2245000
0(
#2250000
b10100010 #
b1011011001110000 $
b0000000001010001 %
1(
#2255000
0(
#2260000
b10100100 #
b1101010001010110 $
b0000000001010010 %
1(
#2265000
0(
#2270000
b10100110 #
b0111011000111001 $
b0000000001010011 %
1(
#2275000
0(
#2280000
b10101000 #
b1000010001001111 $
b0000000001010100 %
1(
#2285000
0(
#2290000
b10101010 #
b1011110011110110 $
b0000000001010101 %
1(
#2295000
0(
#2300000
b10101100 #
b1110100001000101 $
b0000000001010110 %
1(
#2305000
0(
#2310000
b10101110 #
b0101000101001011 $
b0000000001010111 %
1(
#2315000
0(
#2320000
b10110000 #
b0110010110001101 $
b0000000001011000 %
1(
#2325000
0(
#2330000
b10110010 #
b1001010100111111 $
b0000000001011001 %
1(
#2335000
0(
#2340000
b10110100 #
b1111001101001000 $
b0000000001011010 %
1(
#2345000
0(
#2350000
b10110110 #
b1011001000011101 $
b0000000001011011 %
1(
#2355000
0(
#2360000
b10111000 #
b0000001011101000 $
b0000000001011100 %
1(
#2365000
0(
#2370000
b10111010 #
b0001111010011110 $
b0000000001011101 %
1(
#2375000
0(
#2380000
b10111100 #
b1110110011110011 $
b0000000001011110 %
1(
#2385000
0(
#2390000
b10111110 #
b1110001101000111 $
b0000000001011111 %
1(
#2395000
0(
#2400000
b11000000 #
b1110011000000111 $
b0000000001100000 %
1(
#2405000
0(
#2410000
b11000010 #
b0100000100010000 $
b0000000001100001 %
1(
#2415000
0(
#2420000
b11000100 #
b1100000000011101 $
b0000000001100010 %
1(
#2425000
0(
#2430000
b11000110 #
b1001111001000110 $
b0000000001100011 %
1(
#2435000
0(
#2440000
b11001000 #
b1111110000010001 $
b0000000001100100 %
1(
#2445000
0(
#2450000
b11001010 #
b1101110110110001 $
b0000000001100101 %
1(
#2455000
0(
#2460000
b11001100 #
b1110111101100001 $
b0000000001100110 %
1(
#2465000
0(
#2470000
b11001110 #
b1000001111111001 $
b0000000001100111 %
1(
#2475000
0(
#2480000
b11010000 #
b0000001000110100 $
b0000000001101000 %
1(
#2485000
0(
#2490000
b11010010 #
b0100111101000101 $
b0000000001101001 %
1(
#2495000
0(
#2500000
b11010100 #
b0100100110011110 $
b0000000001101010 %
1(
#2505000
0(
#2510000
b11010110 #
b0010010100100100 $
b0000000001101011 %
1(
#2515000
0(
#2520000
b11011000 #
b0000001000100010 $
b0000000001101100 %
1(
#2525000
0(
#2530000
b11011010 #
b0111101010110000 $
b0000000001101101 %
1(
#2535000
0(
#2540000
b11011100 #
b1010111001110111 $
b0000000001101110 %
1(
#2545000
0(
#2550000
b11011110 #
b1001101011110000 $
b0000000001101111 %
1(
#2555000
0(
#2560000
b11100000 #
b1101111010001111 $
b0000000001110000 %
1(
#2565000
0(
#2570000
b11100010 #
b0110111101111110 $
b0000000001110001 %
1(
#2575000
0(
#2580000
b11100100 #
b1110001011010100 $
b0000000001110010 %
1(
#2585000
0(
#2590000
b11100110 #
b1010111101101001 $
b0000000001110011 %
1(
#2595000
0(
#2600000
b11101000 #
b1110111110110100 $
b0000000001110100 %
1(
#2605000
0(
#2610000
b11101010 #
b1001100001011100 $
b0000000001110101 %
1(
#2615000
0(
#2620000
b11101100 #
b0111010101011111 $
b0000000001110110 %
1(
#2625000
0(
#2630000
b11101110 #
b1001010111111111 $
b0000000001110111 %
1(
#2635000
0(
#2640000
b11110000 #
b1010111111001111 $
b0000000001111000 %
1(
#2645000
0(
#2650000
b11110010 #
b0111101110011101 $
b0000000001111001 %
1(
#2655000
0(
#2660000
b11110100 #
b1011001100001000 $
b0000000001111010 %
1(
#2665000
0(
#2670000
b11110110 #
b0011010000000110 $
b0000000001111011 %
1(
#2675000
0(
#2680000
b11111000 #
b0111011110100001 $
b0000000001111100 %
1(
#2685000
0(
#2690000
b11111010 #
b0000101110110110 $
b0000000001111101 %
1(
#2695000
0(
#2700000
b11111100 #
b1010101110000010 $
b0000000001111110 %
1(
#2705000
0(
#2710000
b11111110 #
b1111100100110110 $
b0000000001111111 %
1(
